{"_path":"/items/item-groups","_dir":"items","_draft":false,"_partial":false,"_locale":"","_empty":false,"title":"Custom Item Groups","description":"Now that you've added many items - they should probably be put together.","body":{"type":"root","children":[{"type":"element","tag":"h1","props":{"id":"custom-item-groups"},"children":[{"type":"text","value":"Custom Item Groups"}]},{"type":"element","tag":"p","props":{},"children":[{"type":"text","value":"In the last few pages - you've added quite a few items, it's time to consider making your own item group."}]},{"type":"element","tag":"h2","props":{"id":"creating-the-item-group"},"children":[{"type":"text","value":"Creating the item group."}]},{"type":"element","tag":"p","props":{},"children":[{"type":"text","value":"It's surprisingly easy to create an item group. Simply create a new static final field in your items class to store the item group."}]},{"type":"element","tag":"p","props":{},"children":[{"type":"text","value":"I'll be using the \"Guidite Sword\" from the previous tools tutorial as the icon for the group."}]},{"type":"element","tag":"code","props":{"code":"public static final ItemGroup MY_MOD_ITEMGROUP = FabricItemGroup.builder(new Identifier(\"my_mod\", \"item_group\"))\n    .icon(() -> new ItemStack(ModItems.GUIDITE_SWORD))\n    .build();\n","language":"java","meta":null},"children":[{"type":"element","tag":"pre","props":{},"children":[{"type":"element","tag":"code","props":{"__ignoreMap":""},"children":[{"type":"element","tag":"span","props":{"class":"line","line":1},"children":[{"type":"element","tag":"span","props":{"class":"ct-ee9396"},"children":[{"type":"text","value":"public"}]},{"type":"element","tag":"span","props":{"class":"ct-d71c4e"},"children":[{"type":"text","value":" "}]},{"type":"element","tag":"span","props":{"class":"ct-ee9396"},"children":[{"type":"text","value":"static"}]},{"type":"element","tag":"span","props":{"class":"ct-d71c4e"},"children":[{"type":"text","value":" "}]},{"type":"element","tag":"span","props":{"class":"ct-ee9396"},"children":[{"type":"text","value":"final"}]},{"type":"element","tag":"span","props":{"class":"ct-d71c4e"},"children":[{"type":"text","value":" ItemGroup"}]},{"type":"element","tag":"span","props":{"class":"ct-d63629"},"children":[{"type":"text","value":" "}]},{"type":"element","tag":"span","props":{"class":"ct-d71c4e"},"children":[{"type":"text","value":"MY_MOD_ITEMGROUP"}]},{"type":"element","tag":"span","props":{"class":"ct-d63629"},"children":[{"type":"text","value":" "}]},{"type":"element","tag":"span","props":{"class":"ct-ee9396"},"children":[{"type":"text","value":"="}]},{"type":"element","tag":"span","props":{"class":"ct-d71c4e"},"children":[{"type":"text","value":" FabricItemGroup."}]},{"type":"element","tag":"span","props":{"class":"ct-bcaa2f"},"children":[{"type":"text","value":"builder"}]},{"type":"element","tag":"span","props":{"class":"ct-d71c4e"},"children":[{"type":"text","value":"("}]},{"type":"element","tag":"span","props":{"class":"ct-ee9396"},"children":[{"type":"text","value":"new"}]},{"type":"element","tag":"span","props":{"class":"ct-d71c4e"},"children":[{"type":"text","value":" "}]},{"type":"element","tag":"span","props":{"class":"ct-bcaa2f"},"children":[{"type":"text","value":"Identifier"}]},{"type":"element","tag":"span","props":{"class":"ct-d71c4e"},"children":[{"type":"text","value":"("}]},{"type":"element","tag":"span","props":{"class":"ct-4252a2"},"children":[{"type":"text","value":"\"my_mod\""}]},{"type":"element","tag":"span","props":{"class":"ct-d71c4e"},"children":[{"type":"text","value":", "}]},{"type":"element","tag":"span","props":{"class":"ct-4252a2"},"children":[{"type":"text","value":"\"item_group\""}]},{"type":"element","tag":"span","props":{"class":"ct-d71c4e"},"children":[{"type":"text","value":"))\n"}]}]},{"type":"element","tag":"span","props":{"class":"line","line":2},"children":[{"type":"element","tag":"span","props":{"class":"ct-d71c4e"},"children":[{"type":"text","value":"    ."}]},{"type":"element","tag":"span","props":{"class":"ct-bcaa2f"},"children":[{"type":"text","value":"icon"}]},{"type":"element","tag":"span","props":{"class":"ct-d71c4e"},"children":[{"type":"text","value":"(() "}]},{"type":"element","tag":"span","props":{"class":"ct-ee9396"},"children":[{"type":"text","value":"->"}]},{"type":"element","tag":"span","props":{"class":"ct-d71c4e"},"children":[{"type":"text","value":" "}]},{"type":"element","tag":"span","props":{"class":"ct-ee9396"},"children":[{"type":"text","value":"new"}]},{"type":"element","tag":"span","props":{"class":"ct-d71c4e"},"children":[{"type":"text","value":" "}]},{"type":"element","tag":"span","props":{"class":"ct-bcaa2f"},"children":[{"type":"text","value":"ItemStack"}]},{"type":"element","tag":"span","props":{"class":"ct-d71c4e"},"children":[{"type":"text","value":"(ModItems.GUIDITE_SWORD))\n"}]}]},{"type":"element","tag":"span","props":{"class":"line","line":3},"children":[{"type":"element","tag":"span","props":{"class":"ct-d71c4e"},"children":[{"type":"text","value":"    ."}]},{"type":"element","tag":"span","props":{"class":"ct-bcaa2f"},"children":[{"type":"text","value":"build"}]},{"type":"element","tag":"span","props":{"class":"ct-d71c4e"},"children":[{"type":"text","value":"();"}]}]}]}]}]},{"type":"element","tag":"h2","props":{"id":"adding-items"},"children":[{"type":"text","value":"Adding items."}]},{"type":"element","tag":"p","props":{},"children":[{"type":"text","value":"To add items to the group, you can use the modify item group event similarly to how you added your items to the vanilla item groups:"}]},{"type":"element","tag":"code","props":{"code":"ItemGroupEvents.modifyEntriesEvent(MY_MOD_ITEMGROUP).register(itemGroup -> {\n    itemGroup.add(ModItems.POOP);\n    itemGroup.add(ModItems.GUIDITE_SWORD);\n    // .. other items you've made\n});\n","language":"java","meta":null},"children":[{"type":"element","tag":"pre","props":{},"children":[{"type":"element","tag":"code","props":{"__ignoreMap":""},"children":[{"type":"element","tag":"span","props":{"class":"line","line":1},"children":[{"type":"element","tag":"span","props":{"class":"ct-d71c4e"},"children":[{"type":"text","value":"ItemGroupEvents."}]},{"type":"element","tag":"span","props":{"class":"ct-bcaa2f"},"children":[{"type":"text","value":"modifyEntriesEvent"}]},{"type":"element","tag":"span","props":{"class":"ct-d71c4e"},"children":[{"type":"text","value":"(MY_MOD_ITEMGROUP)."}]},{"type":"element","tag":"span","props":{"class":"ct-bcaa2f"},"children":[{"type":"text","value":"register"}]},{"type":"element","tag":"span","props":{"class":"ct-d71c4e"},"children":[{"type":"text","value":"(itemGroup "}]},{"type":"element","tag":"span","props":{"class":"ct-ee9396"},"children":[{"type":"text","value":"->"}]},{"type":"element","tag":"span","props":{"class":"ct-d71c4e"},"children":[{"type":"text","value":" {\n"}]}]},{"type":"element","tag":"span","props":{"class":"line","line":2},"children":[{"type":"element","tag":"span","props":{"class":"ct-d71c4e"},"children":[{"type":"text","value":"    itemGroup."}]},{"type":"element","tag":"span","props":{"class":"ct-bcaa2f"},"children":[{"type":"text","value":"add"}]},{"type":"element","tag":"span","props":{"class":"ct-d71c4e"},"children":[{"type":"text","value":"(ModItems.POOP);\n"}]}]},{"type":"element","tag":"span","props":{"class":"line","line":3},"children":[{"type":"element","tag":"span","props":{"class":"ct-d71c4e"},"children":[{"type":"text","value":"    itemGroup."}]},{"type":"element","tag":"span","props":{"class":"ct-bcaa2f"},"children":[{"type":"text","value":"add"}]},{"type":"element","tag":"span","props":{"class":"ct-d71c4e"},"children":[{"type":"text","value":"(ModItems.GUIDITE_SWORD);\n"}]}]},{"type":"element","tag":"span","props":{"class":"line","line":4},"children":[{"type":"element","tag":"span","props":{"class":"ct-d71c4e"},"children":[{"type":"text","value":"    "}]},{"type":"element","tag":"span","props":{"class":"ct-ab99ae"},"children":[{"type":"text","value":"// .. other items you've made\n"}]}]},{"type":"element","tag":"span","props":{"class":"line","line":5},"children":[{"type":"element","tag":"span","props":{"class":"ct-d71c4e"},"children":[{"type":"text","value":"});"}]}]}]}]}]},{"type":"element","tag":"hr","props":{},"children":[]},{"type":"element","tag":"p","props":{},"children":[{"type":"text","value":"You should see the item group is now in the creative inventory menu. However, it is untranslated - you must add a translation key to your translations file - similarly to how you translated your first item."}]},{"type":"element","tag":"p","props":{},"children":[{"type":"element","tag":"img","props":{"alt":"","src":"/items/itemgroups_0.png"},"children":[]}]},{"type":"element","tag":"h2","props":{"id":"adding-a-translation-key"},"children":[{"type":"text","value":"Adding a translation key."}]},{"type":"element","tag":"p","props":{},"children":[{"type":"text","value":"The translation key is shown when a translation does not exist, in this case - the translation key is: "},{"type":"element","tag":"code-inline","props":{},"children":[{"type":"text","value":"itemGroup.my_mod.item_group"}]}]},{"type":"element","tag":"code","props":{"code":"{\n    \"itemGroup.my_mod.item_group\": \"Fabric Community Wiki Items\"\n}\n","language":"json","meta":null},"children":[{"type":"element","tag":"pre","props":{},"children":[{"type":"element","tag":"code","props":{"__ignoreMap":""},"children":[{"type":"element","tag":"span","props":{"class":"line","line":1},"children":[{"type":"element","tag":"span","props":{"class":"ct-d71c4e"},"children":[{"type":"text","value":"{\n"}]}]},{"type":"element","tag":"span","props":{"class":"line","line":2},"children":[{"type":"element","tag":"span","props":{"class":"ct-d71c4e"},"children":[{"type":"text","value":"    "}]},{"type":"element","tag":"span","props":{"class":"ct-25ef0d"},"children":[{"type":"text","value":"\"itemGroup.my_mod.item_group\""}]},{"type":"element","tag":"span","props":{"class":"ct-d71c4e"},"children":[{"type":"text","value":": "}]},{"type":"element","tag":"span","props":{"class":"ct-4252a2"},"children":[{"type":"text","value":"\"Fabric Community Wiki Items\"\n"}]}]},{"type":"element","tag":"span","props":{"class":"line","line":3},"children":[{"type":"element","tag":"span","props":{"class":"ct-d71c4e"},"children":[{"type":"text","value":"}"}]}]}]}]}]},{"type":"element","tag":"p","props":{},"children":[{"type":"text","value":"Now, as you can see, the item group should be correctly named:"}]},{"type":"element","tag":"p","props":{},"children":[{"type":"element","tag":"img","props":{"alt":"","src":"/items/itemgroups_1.png"},"children":[]}]},{"type":"element","tag":"h2","props":{"id":"next-steps"},"children":[{"type":"text","value":"Next Steps"}]},{"type":"element","tag":"ul","props":{},"children":[{"type":"element","tag":"li","props":{},"children":[{"type":"text","value":"Why dont you try to make two item groups? One for tools and one specifically for other items?"}]},{"type":"element","tag":"li","props":{},"children":[{"type":"text","value":"Try change the icon to a vanilla item. "},{"type":"element","tag":"em","props":{},"children":[{"type":"text","value":"Vanilla items can be found in the "},{"type":"element","tag":"code-inline","props":{},"children":[{"type":"text","value":"Items"}]},{"type":"text","value":" class"}]}]},{"type":"element","tag":"li","props":{},"children":[{"type":"text","value":"Figure out a way to change the order of the items."}]}]},{"type":"element","tag":"style","children":[{"type":"text","value":".ct-25ef0d{color:#116329}\n.ct-ab99ae{color:#6E7781}\n.ct-4252a2{color:#0A3069}\n.ct-bcaa2f{color:#8250DF}\n.ct-d63629{color:#953800}\n.ct-d71c4e{color:#24292F}\n.ct-ee9396{color:#CF222E}\n.dark .ct-ee9396{color:#FF7B72}\n.dark .ct-d71c4e{color:#C9D1D9}\n.dark .ct-d63629{color:#FFA657}\n.dark .ct-bcaa2f{color:#D2A8FF}\n.dark .ct-4252a2{color:#A5D6FF}\n.dark .ct-ab99ae{color:#8B949E}\n.dark .ct-25ef0d{color:#7EE787}"}]}],"toc":{"title":"","searchDepth":2,"depth":2,"links":[{"id":"creating-the-item-group","depth":2,"text":"Creating the item group."},{"id":"adding-items","depth":2,"text":"Adding items."},{"id":"adding-a-translation-key","depth":2,"text":"Adding a translation key."},{"id":"next-steps","depth":2,"text":"Next Steps"}]}},"_type":"markdown","_id":"content:5.items:4.item-groups.md","_source":"content","_file":"5.items/4.item-groups.md","_extension":"md"}